LICENSE
README.md
pyproject.toml
setup.cfg
setup.py
qredis/__init__.py
qredis/__main__.py
qredis/cli.py
qredis/dialog.py
qredis/editor.py
qredis/panel.py
qredis/qutil.py
qredis/redis.py
qredis/tree.py
qredis/util.py
qredis/window.py
qredis.egg-info/PKG-INFO
qredis.egg-info/SOURCES.txt
qredis.egg-info/dependency_links.txt
qredis.egg-info/entry_points.txt
qredis.egg-info/requires.txt
qredis.egg-info/top_level.txt
qredis/images/__init__.py
qredis/images/folder.png
qredis/images/key.png
qredis/images/redis_logo.png
qredis/ui/MultiEditor.ui
qredis/ui/OpenRedisDialog.ui
qredis/ui/RedisDbEditor.ui
qredis/ui/RedisItemEditor.ui
qredis/ui/RedisTree.ui
qredis/ui/RedisWindow.ui
qredis/ui/SimpleEditor.ui
qredis/ui/StreamViewer.ui
qredis/ui/__init__.py