Metadata-Version: 2.1
Name: qredis
Version: 1.1.0
Summary: Qt based Redis GUI
Home-page: https://github.com/tiagocoutinho/qredis
Author: Tiago Coutinho
Author-email: coutinhotiago@gmail.com
Keywords: redis,GUI,Qt
Classifier: Programming Language :: Python :: 3
Classifier: Programming Language :: Python :: 3.5
Classifier: Programming Language :: Python :: 3.6
Classifier: Programming Language :: Python :: 3.7
Classifier: Programming Language :: Python :: 3.8
Classifier: Programming Language :: Python :: 3.9
Requires-Python: >=3.5
License-File: LICENSE
